{
  "variants": {
    "pressed=false,facing=north": {
      "model": "minecraft:block/torch",
      "y": 270
    },
    "pressed=false,facing=east": {
      "model": "minecraft:block/torch"
    },
    "pressed=false,facing=west": {
      "model": "minecraft:block/torch",
      "y": 180
    },
    "pressed=false,facing=south": {
      "model": "minecraft:block/torch",
      "y": 90
    },
    "pressed=true,facing=north": {
      "model": "infinitybuttons:block/torches/torch",
      "y": 270
    },
    "pressed=true,facing=east": {
      "model": "infinitybuttons:block/torches/torch"
    },
    "pressed=true,facing=west": {
      "model": "infinitybuttons:block/torches/torch",
      "y": 180
    },
    "pressed=true,facing=south": {
      "model": "infinitybuttons:block/torches/torch",
      "y": 90
    }
  }
}